selkie/__init__.py
selkie/__main__.py
selkie/utf8.txt
selkie/_script/__init__.py
selkie/_script/abspath.py
selkie/_script/auth.py
selkie/_script/char.py
selkie/_script/dependencies.py
selkie/_script/doc.py
selkie/_script/doctest.py
selkie/_script/glab.py
selkie/_script/manifest.py
selkie/_script/panlex.py
selkie/cld/__init__.py
selkie/cld/__main__.py
selkie/cld/config.py
selkie/cld/core.py
selkie/cld/toplevel.py
selkie/cld/app/__init__.py
selkie/cld/app/app-scraps.py.disabled
selkie/cld/app/app_scraps.py.disabled
selkie/cld/app/auth.py
selkie/cld/app/cgi.py
selkie/cld/app/client.py
selkie/cld/app/config.py
selkie/cld/app/core.py
selkie/cld/app/dualserver.py
selkie/cld/app/dualserver_full.py
selkie/cld/app/env.py
selkie/cld/app/handler.py
selkie/cld/app/handler_orig.py.ignore
selkie/cld/app/html.py
selkie/cld/app/item.py
selkie/cld/app/log.py
selkie/cld/app/parse.py
selkie/cld/app/request.py
selkie/cld/app/resources.py
selkie/cld/app/response.py
selkie/cld/app/server.py
selkie/cld/app/server2_old.py
selkie/cld/app/server_old.py
selkie/cld/app/session.py.disabled
selkie/cld/app/toplevel.py
selkie/cld/app/ui-scraps.py
selkie/cld/app/ui.py
selkie/cld/app/ui_scraps.py.disabled
selkie/cld/app/weblib.py
selkie/cld/app/wsgi.py
selkie/cld/corpus/__init__.py
selkie/cld/corpus/audio.py.todelete
selkie/cld/corpus/core.py
selkie/cld/corpus/course.py
selkie/cld/corpus/drill.py
selkie/cld/corpus/env.py
selkie/cld/corpus/export.py
selkie/cld/corpus/export_file.py
selkie/cld/corpus/langdb.py
selkie/cld/corpus/language.py
selkie/cld/corpus/lexicon.py
selkie/cld/corpus/media.py
selkie/cld/corpus/rom.py
selkie/cld/corpus/sim.py
selkie/cld/corpus/text.py
selkie/cld/corpus/token-new.py.disabled
selkie/cld/corpus/token.py
selkie/cld/corpus/transcript.py
selkie/cld/corpus/user.py
selkie/cld/db/__init__.py
selkie/cld/db/core.py
selkie/cld/db/dir.py
selkie/cld/db/disk.py
selkie/cld/db/env.py
selkie/cld/db/file.py
selkie/cld/db/meta.py
selkie/cld/db/permissions.py
selkie/cld/glab/__init__.py
selkie-0.25.2.dist-info/METADATA
selkie-0.25.2.dist-info/WHEEL
selkie-0.25.2.dist-info/RECORD
