Metadata-Version: 2.3
Name: selkie
Version: 0.25.2
Summary: Natural language processing and digital language description
Project-URL: Homepage, https://github.com/abney/selkie
Project-URL: Documentation, https://selkie.readthedocs.io/
Project-URL: Bug Tracker, https://github.com/abney/selkie/issues
Author-email: Steven Abney <abney@umich.edu>
Classifier: License :: Other/Proprietary License
Classifier: Operating System :: OS Independent
Classifier: Programming Language :: Python :: 3
Requires-Python: >=3.7
